adrf_flex_fields/__init__.py
adrf_flex_fields/filter_backends.py
adrf_flex_fields/serializers.py
adrf_flex_fields/utils.py
adrf_flex_fields/views.py
adrf_flex_fields-0.1.0.dist-info/METADATA
adrf_flex_fields-0.1.0.dist-info/WHEEL
adrf_flex_fields-0.1.0.dist-info/top_level.txt
adrf_flex_fields-0.1.0.dist-info/RECORD
