Metadata-Version: 2.4
Name: adrf-flex-fields
Version: 0.1.0
Summary: Flexible, dynamic fields and nested models for ADRF (Async Django REST Framework) serializers
Author-email: mushota_243 <mushota_243@users.noreply.github.com>
License: MIT
Project-URL: Homepage, https://github.com/mushota_243/adrf-flex-fields
Project-URL: Documentation, https://github.com/mushota_243/adrf-flex-fields#readme
Project-URL: Repository, https://github.com/mushota_243/adrf-flex-fields
Project-URL: Issues, https://github.com/mushota_243/adrf-flex-fields/issues
Keywords: django,rest,api,adrf,async,serializer,flexible,dynamic
Classifier: Development Status :: 3 - Alpha
Classifier: Intended Audience :: Developers
Classifier: License :: OSI Approved :: MIT License
Classifier: Programming Language :: Python :: 3
Classifier: Programming Language :: Python :: 3.8
Classifier: Programming Language :: Python :: 3.9
Classifier: Programming Language :: Python :: 3.10
Classifier: Programming Language :: Python :: 3.11
Classifier: Programming Language :: Python :: 3.12
Classifier: Framework :: Django
Classifier: Framework :: Django :: 4.1
Classifier: Framework :: Django :: 4.2
Classifier: Framework :: Django :: 5.0
Requires-Python: >=3.8
Requires-Dist: Django>=4.1
Requires-Dist: djangorestframework>=3.14
Requires-Dist: adrf>=0.1.0
Provides-Extra: dev
Requires-Dist: pytest>=7.0; extra == "dev"
Requires-Dist: pytest-asyncio>=0.21; extra == "dev"
Requires-Dist: pytest-django>=4.5; extra == "dev"
Requires-Dist: pytest-cov>=4.0; extra == "dev"
Requires-Dist: hypothesis>=6.0; extra == "dev"
